Metadata-Version: 2.1
Name: wenutils
Version: 0.0.4
Summary: wenutils
Home-page: https://gitee.com/zidanewenqsh/wenutils
Author: ai-046
Author-email: phznai_046@163.com
Project-URL: Bug Tracker, https://gitee.com/zidanewenqsh/wenutils
Classifier: Programming Language :: Python :: 3
Classifier: License :: OSI Approved :: MIT License
Classifier: Operating System :: OS Independent
Requires-Python: >=3.6
License-File: LICENSE
